bocadillo/__init__.py
bocadillo/app_types.py
bocadillo/applications.py
bocadillo/compat.py
bocadillo/config.py
bocadillo/constants.py
bocadillo/converters.py
bocadillo/deprecation.py
bocadillo/error_handlers.py
bocadillo/errors.py
bocadillo/hooks.py
bocadillo/injection.py
bocadillo/middleware.py
bocadillo/plugins.py
bocadillo/redirection.py
bocadillo/request.py
bocadillo/response.py
bocadillo/routing.py
bocadillo/sse.py
bocadillo/staticfiles.py
bocadillo/streaming.py
bocadillo/templates.py
bocadillo/testing.py
bocadillo/urlparse.py
bocadillo/utils.py
bocadillo/views.py
bocadillo/websockets.py
bocadillo/contrib/__init__.py
bocadillo/contrib/pydocmd.py
tasks/__init__.py
tests/__init__.py
tests/conftest.py
tests/test_allowed_hosts.py
tests/test_attachment.py
tests/test_background_tasks.py
tests/test_chunked_response.py
tests/test_config.py
tests/test_converters.py
tests/test_cors.py
tests/test_error_handling.py
tests/test_events.py
tests/test_file_responses.py
tests/test_gzip.py
tests/test_hooks.py
tests/test_hsts.py
tests/test_http.py
tests/test_import.py
tests/test_injection.py
tests/test_json.py
tests/test_json_validation_errors.py
tests/test_methods.py
tests/test_middleware_asgi.py
tests/test_middleware_http.py
tests/test_mount.py
tests/test_plugins.py
tests/test_redirect.py
tests/test_request.py
tests/test_response.py
tests/test_router.py
tests/test_sessions.py
tests/test_sse.py
tests/test_static.py
tests/test_streaming_response.py
tests/test_templates.py
tests/test_utils.py
tests/test_websocket.py
tests/test_wildcard_routes.py
tests/utils.py
bocadillo-0.18.3.dist-info/LICENSE
bocadillo-0.18.3.dist-info/METADATA
bocadillo-0.18.3.dist-info/WHEEL
bocadillo-0.18.3.dist-info/top_level.txt
bocadillo-0.18.3.dist-info/RECORD
