Metadata-Version: 2.1
Name: bocadillo
Version: 0.18.3
Summary: Fast, highly-concurrent and scalable web APIs for everyone
Home-page: https://bocadilloproject.github.io
Author: Florimond Manca
Author-email: florimond.manca@gmail.com
License: MIT
Project-URL: Source, https://github.com/bocadilloproject/bocadillo
Project-URL: Documentation, https://bocadilloproject.github.io
Project-URL: Changelog, https://github.com/bocadilloproject/bocadillo/blob/master/CHANGELOG.md
Platform: UNKNOWN
Classifier: License :: OSI Approved :: MIT License
Classifier: Intended Audience :: Developers
Classifier: Environment :: Web Environment
Classifier: Operating System :: OS Independent
Classifier: Programming Language :: Python :: 3 :: Only
Classifier: Programming Language :: Python :: 3.6
Classifier: Programming Language :: Python :: 3.7
Classifier: Programming Language :: Python :: 3.8
Classifier: Topic :: Software Development :: Libraries :: Application Frameworks
Requires-Python: >=3.6
Requires-Dist: starlette (<0.13,>=0.12.2)
Requires-Dist: uvicorn (<0.9,>=0.7)
Requires-Dist: typesystem (>=0.2.2)
Requires-Dist: jinja2 (>=2.10.1)
Requires-Dist: whitenoise
Requires-Dist: requests
Requires-Dist: python-multipart
Requires-Dist: aiodine (<2.0,>=1.2.5)
Provides-Extra: files
Requires-Dist: aiofiles ; extra == 'files'
Provides-Extra: full
Requires-Dist: aiofiles ; extra == 'full'
Requires-Dist: itsdangerous ; extra == 'full'
Provides-Extra: sessions
Requires-Dist: itsdangerous ; extra == 'sessions'
